neptunecontrib/__init__.py
neptunecontrib/api/__init__.py
neptunecontrib/api/utils.py
neptunecontrib/bots/__init__.py
neptunecontrib/bots/telegram_bot.py
neptunecontrib/hpo/__init__.py
neptunecontrib/hpo/utils.py
neptunecontrib/monitoring/__init__.py
neptunecontrib/monitoring/fairness.py
neptunecontrib/monitoring/fastai.py
neptunecontrib/monitoring/lightgbm.py
neptunecontrib/monitoring/metrics.py
neptunecontrib/monitoring/optuna.py
neptunecontrib/monitoring/sacred.py
neptunecontrib/monitoring/skopt.py
neptunecontrib/monitoring/utils.py
neptunecontrib/monitoring/xgboost_monitor.py
neptunecontrib/sync/__init__.py
neptunecontrib/sync/with_json.py
neptunecontrib/versioning/__init__.py
neptunecontrib/versioning/data.py
neptunecontrib/viz/__init__.py
neptunecontrib/viz/experiments.py
neptunecontrib/viz/parallel_coordinates_plot.py
neptunecontrib/viz/projects.py
neptune_contrib-0.18.0.dist-info/LICENSE
neptune_contrib-0.18.0.dist-info/METADATA
neptune_contrib-0.18.0.dist-info/WHEEL
neptune_contrib-0.18.0.dist-info/top_level.txt
neptune_contrib-0.18.0.dist-info/RECORD
