Metadata-Version: 2.1
Name: neptune-contrib
Version: 0.18.0
Summary: Neptune.ai contributions library
Home-page: https://github.com/neptune-ai/neptune-contrib
Author: neptune.ai
Author-email: contact@neptune.ai
License: MIT License
Platform: UNKNOWN
Requires-Dist: attrdict (>=2.0.0)
Requires-Dist: neptune-client
Requires-Dist: joblib (>=0.13)
Requires-Dist: pandas
Requires-Dist: matplotlib
Requires-Dist: Pillow (>=6.2.0)
Provides-Extra: all
Requires-Dist: python-telegram-bot ; extra == 'all'
Requires-Dist: scikit-optimize (>=0.5.2) ; extra == 'all'
Requires-Dist: scipy ; extra == 'all'
Requires-Dist: sacred (>=0.7.5) ; extra == 'all'
Requires-Dist: scikit-learn (>=0.21.3) ; extra == 'all'
Requires-Dist: scikit-plot (>=0.3.7) ; extra == 'all'
Requires-Dist: seaborn (>=0.8.1) ; extra == 'all'
Requires-Dist: aif360 (>=0.2.1) ; extra == 'all'
Requires-Dist: xgboost (>=0.82) ; extra == 'all'
Requires-Dist: boto3 ; extra == 'all'
Requires-Dist: numpy ; extra == 'all'
Requires-Dist: altair (>=2.3.0) ; extra == 'all'
Requires-Dist: hiplot (>=0.1.5) ; extra == 'all'
Provides-Extra: bots
Requires-Dist: python-telegram-bot ; extra == 'bots'
Provides-Extra: hpo
Requires-Dist: scikit-optimize (>=0.5.2) ; extra == 'hpo'
Requires-Dist: scipy ; extra == 'hpo'
Provides-Extra: monitoring
Requires-Dist: scikit-optimize (>=0.5.2) ; extra == 'monitoring'
Requires-Dist: sacred (>=0.7.5) ; extra == 'monitoring'
Requires-Dist: scikit-learn (>=0.21.3) ; extra == 'monitoring'
Requires-Dist: scikit-plot (>=0.3.7) ; extra == 'monitoring'
Requires-Dist: seaborn (>=0.8.1) ; extra == 'monitoring'
Requires-Dist: aif360 (>=0.2.1) ; extra == 'monitoring'
Requires-Dist: xgboost (>=0.82) ; extra == 'monitoring'
Provides-Extra: versioning
Requires-Dist: boto3 ; extra == 'versioning'
Requires-Dist: numpy ; extra == 'versioning'
Provides-Extra: viz
Requires-Dist: altair (>=2.3.0) ; extra == 'viz'
Requires-Dist: hiplot (>=0.1.5) ; extra == 'viz'
